[
    {
        "name": "Giannis Antetokounmpo",
        "position": "Forward",
        "height": "6' 11\"",
        "weight": "243lbs",
        "number": 34,
        "team": "MILWAUKEE BUCKS",
        "img": "https://cdn.nba.com/headshots/nba/latest/1040x760/203507.png"

    },
    {
        "name": "Kobe Bryant",
        "position": "Guard",
        "height": "6' 6\"",
        "weight": "212lbs",
        "number": 8,
        "team": "LOS ANGELES LAKERS",
        "img": "https://cdn.nba.com/headshots/nba/latest/1040x760/977.png"

    },
    {
        "name": "Trae Young",
        "number": 11,
        "img": "https://cdn.nba.com/headshots/nba/latest/1040x760/1629027.png"
    }
]